{
    "url": "https://www.dmv.virginia.gov/vehicles/registration/surplus",
    "title": "Military Surplus Motor Vehicles",
    "text_content": "What qualifies as a military surplus motor vehicle (MSMV)? What license plate options are available for MSMVs in Virginia? What are the driving restrictions for MSMVs with military surplus license plates? What are the penalties for violating MSMV driving restrictions? How can an MSMV owner apply for a military surplus license plate? DMV, military surplus motor vehicle, MSMV, license plate, VSA 10M, driving restrictions, Virginia Code, off-road, misdemeanor, registration revocation # Main Content\nWhat qualifies as a military surplus motor vehicle (MSMV)?\nA MSMV is a multi-purpose or tactical vehicle manufactured by, or under the direction of the United States Armed Forces, for off-road use and subsequently authorized for sale to civilians. This does not include trailers or semi-trailers.\nWhat are the license plate options for MSMVs?\nIf you already have a registered MSMV, you may continue to register for a standard or special license plate for as long as you own the vehicle.\nIf you register an MSMV between July 1, 2018 and December 31, 2018, you can obtain one of two license plates:\nMilitary surplus license plate \u2013 owner must complete form\nVSA 10M\ncertifying their use of a second vehicle for daily travel and pay a one-time $100 fee. MSMV driving restrictions apply.\nStandard or special license plate \u2013 owner must show proof of a current Virginia safety inspection.\nIf you register a MSMV after December 31, 2018, you are only eligible for military surplus license plates. An owner must complete form\nVSA 10M\nand pay a one-time $100 fee. MSMV driving restrictions apply.\nMSMV driving restrictions\nVirginia Code \u00a7 46.2-730.1 limits MSMV with military surplus license plates to the participation in off-road events, on-road club activities, exhibits, tours, parades, and similar events. MSMV may also be used on the highways of the Commonwealth for the purpose of selling the vehicle and obtaining repairs or maintenance. Military surplus license plates permit occasional pleasure driving (not to exceed 125 miles from the address at which the vehicle is stored for use) but cannot be used for general transportation purposes, including, but not limited to, daily travel to and from the owner\u2019s place of employment. Occasional pleasure driving amounts to a 250 mile round trip.\nViolations of military surplus motor vehicle rules\nAny owner of a MSMV registered with license plates pursuant to Virginia Code \u00a7 46.2-730.1 will be guilty of a Class 4 misdemeanor if convicted of a violation of military plate usage. The conviction will cause the owner\u2019s registration for the vehicle involved in the violation to be revoked for a five year period from the date of conviction.",
    "attachments": {
        "vsa10m.pdf": "attachments\\vsa10m.pdf",
        "dmv201.pdf": "attachments\\dmv201.pdf"
    }
}